{
    "memory": [
        {
            "base": 1048576,
            "size": 267386880
        },
        {
            "base": 303370240,
            "size": 1673691136
        },
        {
            "base": 2036105216,
            "size": 352256
        },
        {
            "base": 2040844288,
            "size": 13807616
        },
        {
            "base": 2055356416,
            "size": 4046848
        },
        {
            "base": 4294967296,
            "size": 6442450944
        }
    ],
    "kdevs": [
        {
            "name": "apic",
            "base": 4276092928,
            "size": 4096
        },
        {
            "name": "ioapic.0",
            "base": 4273995776,
            "size": 4096
        },
        {
            "name": "drhu.0",
            "base": 4275453952,
            "size": 4096
        },
        {
            "name": "drhu.1",
            "base": 4275458048,
            "size": 4096
        }
    ],
    "rmrrs": [
        {
            "devid": 168,
            "base":  2035703808,
            "limit": 2035834879
        },
        {
            "devid": 16,
            "base":  2071986176,
            "limit": 2147483647
        }
    ],
    "bootinfo": {
        "numIOPTLevels": 4
    }
}
